megasdkrestclient/__init__.py
megasdkrestclient/async_client.py
megasdkrestclient/client.py
megasdkrestclient/constants.py
megasdkrestclient/errors.py
megasdkrestclient/utils.py
megasdkrestclient-0.1.1.dist-info/METADATA
megasdkrestclient-0.1.1.dist-info/WHEEL
megasdkrestclient-0.1.1.dist-info/top_level.txt
megasdkrestclient-0.1.1.dist-info/RECORD
