Metadata-Version: 2.1
Name: megasdkrestclient
Version: 0.1.1
Summary: MegaSDK-REST python wrapper
Home-page: https://github.com/jaskaranSM/megasdkrestclient
License: UNKNOWN
Download-URL: https://github.com/jaskaranSM/megasdkrestclient/releases
Platform: UNKNOWN
Classifier: Programming Language :: Python :: 3
Classifier: License :: OSI Approved :: GNU Lesser General Public License v3 (LGPLv3)
Classifier: Operating System :: OS Independent
Requires-Python: >=3.6
Requires-Dist: requests
Requires-Dist: aiohttp
